LICENSE
README.md
main.py
setup.cfg
setup.py
uft.egg-info/PKG-INFO
uft.egg-info/SOURCES.txt
uft.egg-info/dependency_links.txt
uft.egg-info/entry_points.txt
uft.egg-info/top_level.txt