Metadata-Version: 2.1
Name: uft
Version: 2.0.3
Summary: UFT (Universal File Transfer) is a CLI tool , which can be used to upload files to a public server and any one can download it...
Home-page: https://github.com/darkmash-org/UFT
Author: Cactochan
License: UNKNOWN
Keywords: ["uft","universal","file","transfer"]
Platform: any
Classifier: Programming Language :: Python :: 3
Requires-Python: >=3.8
License-File: LICENSE
